bindr/__init__.py
bindr-0.1.1.dist-info/LICENSE
bindr-0.1.1.dist-info/METADATA
bindr-0.1.1.dist-info/WHEEL
bindr-0.1.1.dist-info/top_level.txt
bindr-0.1.1.dist-info/RECORD
